myLib/myLib.py
myLib/myuseLib.py
kkm230508_AILib-0.0.4.dist-info/METADATA
kkm230508_AILib-0.0.4.dist-info/WHEEL
kkm230508_AILib-0.0.4.dist-info/requirements.txt
kkm230508_AILib-0.0.4.dist-info/top_level.txt
kkm230508_AILib-0.0.4.dist-info/RECORD
